[
    {
      "id": 1,
      "image": "Aragorn.jpg"
    },
    {
      "id": 2,
      "image": "Frodo.jpg"    
    },
    {
      "id": 3,
      "image": "Gandalf.jpg"
    },
    {
      "id": 4,
      "image": "Gimli.jpg" 
    },
    {
      "id": 5,
      "image": "Golumn.jpg"
    },
    {
      "id": 6,
      "image": "Girl.jpg"
    },
    {
      "id": 7,
      "image": "Lego.jpg"
    },
    {
      "id": 8,
      "image": "Goul.jpg"
    },
    {
      "id": 9,
      "image": "Sam.jpeg"
    },
    {
      "id": 10,
      "image": "Eye.jpg"
    },
    {
      "id": 11,
      "image": "SaMan.jpg"
    },
    {
      "id": 12,
      "image": "Tree.jpeg"
    }
  ]
  